<?xml version = "1.0" encoding = "UTF-8"?>
<root>
	<object name = "SteelMonstersParams">
		<object name="Ships">
			<object name="Kagero2">
				<float name="AccelRate" value="4.e-004"/>
				<integer name="AirplanesCount" value="0"/>
				<string name="AmmoLoadingTemplate" value="Ammo 20"/>
				<boolean name="BoatsTransportationAbility" value="false"/>
				<integer name="CabinArmor" value="20"/>
				<boolean name="CanBeChanged" value="true"/>
				<boolean name="CanUseTorpedos" value="true"/>
				<integer name="Country" value="2"/>
				<integer name="Crew" value="240"/>
				<float name="CriticalCareen" value="27."/>
				<float name="CriticalDFT" value="0.7"/>
				<float name="CriticalDifferent" value="2.5"/>
				<float name="DisplacementMax" value="2600."/>
				<float name="DTimeProd" value="50."/>
				<float name="EPR" value="125."/>
				<float name="FireRisk" value="167."/>
				<float name="Fuel" value="500."/>
				<float name="HLShapeCoef" value="0.9"/>
				<integer name="HullArmorSide" value="20"/>
				<integer name="HullArmorTop" value="20"/>
				<float name="Iron" value="2700."/>
				<integer name="Length" value="118.5"/>
				<float name="MaxSpeed" value="35."/>
				<integer name="MinCrew" value="90"/>
				<float name="Money" value="4400."/>
				<string name="Name" value="Kagero2"/>
				<boolean name="New" value="true"/>
				<float name="NTimeProd" value="140."/>
				<integer name="Nuc_Dest_Prob" value="700"/>
				<integer name="Passengers" value="30"/>
				<boolean name="PlanesTransportationAbility" value="false"/>
				<float name="Range" value="9000."/>
				<integer name="Rank" value="5"/>
				<string name="SMU" value="Kagero2"/>
				<float name="Speed" value="18."/>
				<float name="StoreCapacity" value="220."/>
				<boolean name="Transportable" value="false"/>
				<float name="TurnRate" value="1.8e-003"/>
				<integer name="Type" value="4"/>
				<float name="Vitality" value="830."/>
				<float name="VitalityAA" value="400."/>
				<float name="Weight" value="2033."/>
				<integer name="Width" value="10.8"/>
				<integer name="Year" value="39"/>
			</object>
		</object>
		<object name="Hit_Location">
			<object name="K2596">
				<integer name="Country" value="2"/>
				<float name="ER" value="100."/>
				<string name="Hull" value="Kagero2_Ordinari"/>
				<string name="Name" value="Bow1_Bottom"/>
				<string name="TypHL" value="Hull"/>
				<string name="UnitName" value="Kagero2"/>
			</object>
			<object name="K2597">
				<integer name="Country" value="2"/>
				<float name="ER" value="100."/>
				<string name="Hull" value="Kagero2_Ordinari"/>
				<string name="Name" value="Bow1_Deck"/>
				<string name="TypHL" value="Hull"/>
				<string name="UnitName" value="Kagero2"/>
			</object>
			<object name="K2598">
				<integer name="Country" value="2"/>
				<float name="ER" value="100."/>
				<string name="Hull" value="Kagero2_Ordinari"/>
				<string name="Name" value="Stern2"/>
				<string name="TypHL" value="Hull"/>
				<string name="UnitName" value="Kagero2"/>
			</object>
			<object name="K2599">
				<integer name="Country" value="2"/>
				<float name="ER" value="100."/>
				<string name="Hull" value="Kagero2_Ordinari"/>
				<string name="Name" value="Tiller"/>
				<string name="TypHL" value="Hull"/>
				<string name="UnitName" value="Kagero2"/>
			</object>
			<object name="K2600">
				<string name="ConnectName" value="Engine1"/>
				<integer name="Country" value="2"/>
				<float name="ER" value="100."/>
				<string name="Hull" value="FletcherMover"/>
				<string name="Name" value="Mover1"/>
				<string name="TypHL" value="Mover"/>
				<string name="UnitName" value="Kagero2"/>
			</object>
			<object name="K2601">
				<string name="ConnectName" value="Engine2"/>
				<integer name="Country" value="2"/>
				<float name="ER" value="100."/>
				<string name="Hull" value="FletcherMover"/>
				<string name="Name" value="Mover2"/>
				<string name="TypHL" value="Mover"/>
				<string name="UnitName" value="Kagero2"/>
			</object>
			<object name="K2602">
				<string name="ConnectName" value="Tiller"/>
				<integer name="Country" value="2"/>
				<float name="ER" value="100."/>
				<string name="Hull" value="FletcherMover"/>
				<string name="Name" value="Rudder"/>
				<string name="TypHL" value="Rudder"/>
				<string name="UnitName" value="Kagero2"/>
			</object>
			<object name="K2603">
				<integer name="Country" value="2"/>
				<float name="ER" value="100."/>
				<string name="Hull" value="Kagero2_AmmoStore"/>
				<string name="Name" value="AmmoStore_MG_1"/>
				<float name="Param_1" value="0."/>
				<string name="TypHL" value="AmmoStore"/>
				<string name="UnitName" value="Kagero2"/>
			</object>
			<object name="K2604">
				<integer name="Country" value="2"/>
				<integer name="Crew" value="125"/>
				<float name="ER" value="100."/>
				<string name="Hull" value="Kagero2_Ordinari"/>
				<string name="Name" value="BattleCabin"/>
				<string name="TypHL" value="Crew"/>
				<string name="UnitName" value="Kagero2"/>
			</object>
			<object name="K2605">
				<integer name="Country" value="2"/>
				<float name="ER" value="100."/>
				<string name="Hull" value="Kagero2_Ordinari"/>
				<string name="Name" value="Probe_Torpedos"/>
				<string name="TypHL" value="Probe"/>
				<string name="UnitName" value="Kagero2"/>
			</object>
			<object name="K2606">
				<integer name="Country" value="2"/>
				<integer name="Crew" value="125"/>
				<float name="ER" value="100."/>
				<string name="Hull" value="FletcherOrdinary"/>
				<string name="Name" value="ConingBridge"/>
				<string name="TypHL" value="Crew"/>
				<string name="UnitName" value="Kagero2"/>
			</object>
			<object name="K2607">
				<integer name="Country" value="2"/>
				<float name="ER" value="100."/>
				<string name="Hull" value="Kagero2_Ordinari"/>
				<string name="Name" value="Bow2_LBoard_Lower"/>
				<string name="TypHL" value="Hull"/>
				<string name="UnitName" value="Kagero2"/>
			</object>
			<object name="K2608">
				<integer name="Country" value="2"/>
				<float name="ER" value="100."/>
				<string name="Hull" value="Kagero2_Ordinari"/>
				<string name="Name" value="Sonar"/>
				<string name="TypHL" value="Probe"/>
				<string name="UnitName" value="Kagero2"/>
			</object>
			<object name="K2609">
				<integer name="Country" value="2"/>
				<float name="ER" value="100."/>
				<string name="Hull" value="Kagero2_Ordinari"/>
				<string name="Name" value="Bow2_RBoard_Lower"/>
				<string name="TypHL" value="Hull"/>
				<string name="UnitName" value="Kagero2"/>
			</object>
			<object name="K2610">
				<integer name="Country" value="2"/>
				<float name="ER" value="100."/>
				<string name="Hull" value="Kagero2_Ordinari"/>
				<string name="Name" value="Bow2_LBoard_Upper"/>
				<string name="TypHL" value="Hull"/>
				<string name="UnitName" value="Kagero2"/>
			</object>
			<object name="K2611">
				<integer name="Country" value="2"/>
				<float name="ER" value="100."/>
				<string name="Hull" value="Kagero2_Ordinari"/>
				<string name="Name" value="Bow2_Deck"/>
				<string name="TypHL" value="Hull"/>
				<string name="UnitName" value="Kagero2"/>
			</object>
			<object name="K2612">
				<integer name="Country" value="2"/>
				<float name="ER" value="100."/>
				<string name="Hull" value="Kagero2_Ordinari"/>
				<string name="Name" value="Bow2_RBoard_Upper"/>
				<string name="TypHL" value="Hull"/>
				<string name="UnitName" value="Kagero2"/>
			</object>
			<object name="K2613">
				<integer name="Country" value="2"/>
				<float name="ER" value="100."/>
				<string name="Hull" value="Kagero2_Ordinari"/>
				<string name="Name" value="Probe_MG"/>
				<string name="TypHL" value="Probe"/>
				<string name="UnitName" value="Kagero2"/>
			</object>
			<object name="K2614">
				<integer name="Country" value="2"/>
				<float name="ER" value="100."/>
				<string name="Hull" value="Kagero2_Ordinari"/>
				<string name="Name" value="Probe_Radio"/>
				<string name="TypHL" value="Probe"/>
				<string name="UnitName" value="Kagero2"/>
			</object>
			<object name="K2615">
				<integer name="Country" value="2"/>
				<float name="ER" value="100."/>
				<string name="Hull" value="Kagero2_Ordinari"/>
				<string name="Name" value="Probe_Radar"/>
				<string name="TypHL" value="Probe"/>
				<string name="UnitName" value="Kagero2"/>
			</object>
			<object name="K2616">
				<integer name="Country" value="2"/>
				<float name="ER" value="100."/>
				<string name="Hull" value="Kagero2_Ordinari"/>
				<string name="Name" value="Middle1_RBoard_Lower"/>
				<string name="TypHL" value="FuelTank"/>
				<string name="UnitName" value="Kagero2"/>
			</object>
			<object name="K2617">
				<integer name="Country" value="2"/>
				<float name="ER" value="100."/>
				<string name="Hull" value="Kagero2_MTO"/>
				<string name="Name" value="Middle1_BoilerCover"/>
				<string name="TypHL" value="Hull"/>
				<string name="UnitName" value="Kagero2"/>
			</object>
			<object name="K2618">
				<integer name="Country" value="2"/>
				<float name="ER" value="100."/>
				<string name="Hull" value="Std_Boiler"/>
				<string name="Name" value="Boiler1"/>
				<string name="TypHL" value="Boiler"/>
				<string name="UnitName" value="Kagero2"/>
			</object>
			<object name="K2619">
				<integer name="Country" value="2"/>
				<float name="ER" value="100."/>
				<string name="Hull" value="Kagero2_Ordinari"/>
				<string name="Name" value="Middle1_LBoard_Lower"/>
				<string name="TypHL" value="FuelTank"/>
				<string name="UnitName" value="Kagero2"/>
			</object>
			<object name="K2620">
				<integer name="Country" value="2"/>
				<float name="ER" value="100."/>
				<string name="Hull" value="Kagero2_Ordinari"/>
				<string name="Name" value="Middle1_RBoard_Upper"/>
				<string name="TypHL" value="Hull"/>
				<string name="UnitName" value="Kagero2"/>
			</object>
			<object name="K2621">
				<integer name="Country" value="2"/>
				<float name="ER" value="100."/>
				<string name="Hull" value="Kagero2_Ordinari"/>
				<string name="Name" value="Middle1_LBoard_Upper"/>
				<string name="TypHL" value="Hull"/>
				<string name="UnitName" value="Kagero2"/>
			</object>
			<object name="K2622">
				<integer name="Country" value="2"/>
				<float name="ER" value="100."/>
				<string name="Hull" value="Kagero2_Ordinari"/>
				<string name="Name" value="Middle2_LBoard_Lower"/>
				<string name="TypHL" value="FuelTank"/>
				<string name="UnitName" value="Kagero2"/>
			</object>
			<object name="K2623">
				<integer name="Country" value="2"/>
				<float name="ER" value="100."/>
				<string name="Hull" value="Kagero2_MTO"/>
				<string name="Name" value="Middle2_BoilerCover"/>
				<string name="TypHL" value="Hull"/>
				<string name="UnitName" value="Kagero2"/>
			</object>
			<object name="K2624">
				<integer name="Country" value="2"/>
				<float name="ER" value="100."/>
				<string name="Hull" value="Std_Boiler"/>
				<string name="Name" value="Boiler2"/>
				<string name="TypHL" value="Boiler"/>
				<string name="UnitName" value="Kagero2"/>
			</object>
			<object name="K2625">
				<integer name="Country" value="2"/>
				<float name="ER" value="100."/>
				<string name="Hull" value="Kagero2_Ordinari"/>
				<string name="Name" value="Middle2_LBoard_Upper"/>
				<string name="TypHL" value="Hull"/>
				<string name="UnitName" value="Kagero2"/>
			</object>
			<object name="K2626">
				<integer name="Country" value="2"/>
				<float name="ER" value="100."/>
				<string name="Hull" value="Kagero2_Ordinari"/>
				<string name="Name" value="Middle2_RBoard_Lower"/>
				<string name="TypHL" value="FuelTank"/>
				<string name="UnitName" value="Kagero2"/>
			</object>
			<object name="K2627">
				<integer name="Country" value="2"/>
				<float name="ER" value="100."/>
				<string name="Hull" value="Kagero2_Ordinari"/>
				<string name="Name" value="Middle2_RBoard_Upper"/>
				<string name="TypHL" value="Hull"/>
				<string name="UnitName" value="Kagero2"/>
			</object>
			<object name="K2628">
				<integer name="Country" value="2"/>
				<float name="ER" value="100."/>
				<string name="Hull" value="Kagero2_Ordinari"/>
				<string name="Name" value="Middle3_LBoard_Lower"/>
				<string name="TypHL" value="FuelTank"/>
				<string name="UnitName" value="Kagero2"/>
			</object>
			<object name="K2629">
				<integer name="Country" value="2"/>
				<float name="ER" value="100."/>
				<string name="Hull" value="Kagero2_Ordinari"/>
				<string name="Name" value="Middle3_LBoard_Upper"/>
				<string name="TypHL" value="Hull"/>
				<string name="UnitName" value="Kagero2"/>
			</object>
			<object name="K2630">
				<integer name="Country" value="2"/>
				<float name="ER" value="100."/>
				<string name="Hull" value="Kagero2_MTO"/>
				<string name="Name" value="Middle3_BoilerCover"/>
				<string name="TypHL" value="Hull"/>
				<string name="UnitName" value="Kagero2"/>
			</object>
			<object name="K2631">
				<integer name="Country" value="2"/>
				<float name="ER" value="100."/>
				<string name="Hull" value="Std_Boiler"/>
				<string name="Name" value="Boiler3"/>
				<string name="TypHL" value="Boiler"/>
				<string name="UnitName" value="Kagero2"/>
			</object>
			<object name="K2632">
				<integer name="Country" value="2"/>
				<float name="ER" value="100."/>
				<string name="Hull" value="Kagero2_Ordinari"/>
				<string name="Name" value="Middle3_RBoard_Upper"/>
				<string name="TypHL" value="Hull"/>
				<string name="UnitName" value="Kagero2"/>
			</object>
			<object name="K2633">
				<integer name="Country" value="2"/>
				<float name="ER" value="100."/>
				<string name="Hull" value="Kagero2_Ordinari"/>
				<string name="Name" value="Middle3_RBoard_Lower"/>
				<string name="TypHL" value="FuelTank"/>
				<string name="UnitName" value="Kagero2"/>
			</object>
			<object name="K2634">
				<integer name="Country" value="2"/>
				<float name="ER" value="100."/>
				<string name="Hull" value="Kagero2_Ordinari"/>
				<string name="Name" value="Middle4_LBoard_Lower"/>
				<string name="TypHL" value="FuelTank"/>
				<string name="UnitName" value="Kagero2"/>
			</object>
			<object name="K2635">
				<integer name="Country" value="2"/>
				<float name="ER" value="100."/>
				<string name="Hull" value="Kagero2_MTO"/>
				<string name="Name" value="Middle4_LEngineCover"/>
				<string name="TypHL" value="Hull"/>
				<string name="UnitName" value="Kagero2"/>
			</object>
			<object name="K2636">
				<integer name="Country" value="2"/>
				<float name="ER" value="100."/>
				<string name="Hull" value="Kagero2_MTO"/>
				<string name="Name" value="Middle4_REngineCover"/>
				<string name="TypHL" value="Hull"/>
				<string name="UnitName" value="Kagero2"/>
			</object>
			<object name="K2637">
				<integer name="Country" value="2"/>
				<float name="ER" value="100."/>
				<string name="Hull" value="Kagero2_Ordinari"/>
				<string name="Name" value="Middle4_RBoard_Upper"/>
				<string name="TypHL" value="Hull"/>
				<string name="UnitName" value="Kagero2"/>
			</object>
			<object name="K2638">
				<integer name="Country" value="2"/>
				<float name="ER" value="100."/>
				<string name="Hull" value="Kagero2_Ordinari"/>
				<string name="Name" value="Middle4_UpperDeck"/>
				<string name="TypHL" value="Hull"/>
				<string name="UnitName" value="Kagero2"/>
			</object>
			<object name="K2639">
				<integer name="Country" value="2"/>
				<float name="ER" value="100."/>
				<string name="Hull" value="Kagero2_Ordinari"/>
				<string name="Name" value="Middle4_LBoard_Upper"/>
				<string name="TypHL" value="Hull"/>
				<string name="UnitName" value="Kagero2"/>
			</object>
			<object name="K2640">
				<integer name="Country" value="2"/>
				<float name="ER" value="100."/>
				<string name="Hull" value="Kagero2_Ordinari"/>
				<string name="Name" value="Middle4_RBoard_Lower"/>
				<string name="TypHL" value="FuelTank"/>
				<string name="UnitName" value="Kagero2"/>
			</object>
			<object name="K2641">
				<integer name="Country" value="2"/>
				<float name="ER" value="100."/>
				<string name="Hull" value="Kagero2_AmmoStore"/>
				<string name="Name" value="AmmoStore_Torpedos"/>
				<float name="Param_1" value="0."/>
				<string name="TypHL" value="AmmoStore"/>
				<string name="UnitName" value="Kagero2"/>
			</object>
			<object name="K2642">
				<string name="ConnectName" value="Boiler1;Boiler2;Boiler3"/>
				<integer name="Country" value="2"/>
				<float name="ER" value="100."/>
				<string name="Hull" value="Std_Boiler"/>
				<string name="Name" value="Engine2"/>
				<string name="TypHL" value="Engine"/>
				<string name="UnitName" value="Kagero2"/>
			</object>
			<object name="K2643">
				<string name="ConnectName" value="Boiler1;Boiler2;Boiler3"/>
				<integer name="Country" value="2"/>
				<float name="ER" value="100."/>
				<string name="Hull" value="Std_Boiler"/>
				<string name="Name" value="Engine1"/>
				<string name="TypHL" value="Engine"/>
				<string name="UnitName" value="Kagero2"/>
			</object>
			<object name="K2644">
				<integer name="Country" value="2"/>
				<float name="ER" value="100."/>
				<string name="Hull" value="Kagero2_Ordinari"/>
				<string name="Name" value="Stern1_Bottom"/>
				<string name="TypHL" value="Hull"/>
				<string name="UnitName" value="Kagero2"/>
			</object>
			<object name="K2645">
				<integer name="Country" value="2"/>
				<float name="ER" value="100."/>
				<string name="Hull" value="Kagero2_AmmoStore"/>
				<string name="Name" value="AmmoStore_MG_2"/>
				<float name="Param_1" value="0."/>
				<string name="TypHL" value="AmmoStore"/>
				<string name="UnitName" value="Kagero2"/>
			</object>
			<object name="K2646">
				<integer name="Country" value="2"/>
				<float name="ER" value="100."/>
				<string name="Hull" value="Kagero2_AmmoStore"/>
				<string name="Name" value="AmmoStore_MG_3"/>
				<float name="Param_1" value="0."/>
				<string name="TypHL" value="AmmoStore"/>
				<string name="UnitName" value="Kagero2"/>
			</object>
			<object name="K2647">
				<integer name="Country" value="2"/>
				<float name="ER" value="100."/>
				<string name="Hull" value="Kagero2_Ordinari"/>
				<string name="Name" value="Stern1_UpperDeck"/>
				<string name="TypHL" value="Hull"/>
				<string name="UnitName" value="Kagero2"/>
			</object>
			<object name="K29307">
				<integer name="Country" value="2"/>
				<float name="ER" value="100."/>
				<string name="Hull" value="Std_Hull"/>
				<string name="Name" value="SternSmokeStack"/>
				<string name="TypHL" value="Hull"/>
				<string name="UnitName" value="Kagero2"/>
			</object>
			<object name="K29308">
				<integer name="Country" value="2"/>
				<float name="ER" value="100."/>
				<string name="Hull" value="Std_Hull"/>
				<string name="Name" value="BowSmokeStack"/>
				<string name="TypHL" value="Hull"/>
				<string name="UnitName" value="Kagero2"/>
			</object>
		</object>
		<object name="Hulls">
			<object name="Kagero2_AmmoStore">
				<integer name="Back" value="45"/>
				<integer name="Bottom" value="45"/>
				<integer name="Country" value="2"/>
				<float name="ExplProb" value="20."/>
				<float name="FireProb" value="20."/>
				<integer name="Front" value="45"/>
				<integer name="Left" value="45"/>
				<string name="Material" value="Armored"/>
				<integer name="Right" value="45"/>
				<integer name="Top" value="45"/>
				<integer name="UnitName" value="0"/>
				<string name="UnitTyp" value="Ship"/>
			</object>
			<object name="Kagero2_MTO">
				<integer name="Back" value="20"/>
				<integer name="Bottom" value="20"/>
				<integer name="Country" value="2"/>
				<float name="ExplProb" value="0."/>
				<float name="FireProb" value="30."/>
				<integer name="Front" value="20"/>
				<integer name="Left" value="20"/>
				<string name="Material" value="Armored"/>
				<integer name="Right" value="20"/>
				<integer name="Top" value="20"/>
				<integer name="UnitName" value="0"/>
				<string name="UnitTyp" value="Ship"/>
			</object>
			<object name="Kagero2_Ordinari">
				<integer name="Back" value="25"/>
				<integer name="Bottom" value="25"/>
				<integer name="Country" value="2"/>
				<float name="ExplProb" value="0."/>
				<float name="FireProb" value="15."/>
				<integer name="Front" value="25"/>
				<integer name="Left" value="25"/>
				<string name="Material" value="Steel"/>
				<integer name="Right" value="25"/>
				<integer name="Top" value="25"/>
				<integer name="UnitName" value="0"/>
				<string name="UnitTyp" value="Ship"/>
			</object>
		</object>
		<object name="ShipsNames">
			<object name="Kagero2">
				<string name="1" value="Kagero21"/>
				<string name="2" value="Kagero22"/>	
				<string name="3" value="Kagero23"/>
				<string name="4" value="Kagero24"/>
				<string name="5" value="Kagero25"/>
				<string name="6" value="Kagero26"/>
				<string name="7" value="Kagero27"/>
				<string name="8" value="Kagero28"/>	
				<string name="9" value="Kagero29"/>
				<string name="10" value="Kagero210"/>
				<string name="11" value="Kagero211"/>
				<string name="12" value="Kagero212"/>
				<string name="13" value="Kagero213"/>
				<string name="14" value="Kagero214"/>
				<string name="15" value="Kagero215"/>
				<string name="16" value="Kagero216"/>
				<string name="17" value="Kagero217"/>
				<string name="18" value="Kagero218"/>
			</object>
		</object>
		<object name="UnitsByType">
			<object name="4">
				<object name="Kagero2">
					<string name="ChildTable" value="Ships"/>
				</object>
			</object>
		</object>
	</object>
</root>
